{
  "id": 7,
  "title": "Εξαφανίστηκε από την Καραϊβική η φώκια μονάχους",
  "slug": "exafanistike-apo-tin-karaiviki-i-fokia-monachoys-7",
  "sectionId": 1,
  "sectionTitle": "Ειδήσεις",
  "sectionSlug": "eidiseis-1",
  "categoryId": 1,
  "categoryTitle": "Τελευταία",
  "categorySlug": "teleytaia-1",
  "date": "2004-07-07T00:00:00",
  "created": "2006-12-29T00:00:00",
  "published": true,
  "state": 1,
  "frontpage": false,
  "hits": 1405,
  "excerpt": "Αντίο για πάντα Μόνο οι φωτογραφίες απομένουν... Η φώκια μονάχους της Καραϊβικής , στενός συγγενής της μεσογειακής φώκιας , ακολούθησε το δρόμο πολλών ακόμα ειδών και εξαφανίστηκε για πάντα , επιβεβαίωσαν ομοσπονδιακοί α",
  "html": "<p class=\"MsoNormal\" style=\"text-align: left\" align=\"left\">\r\n<b><span style=\"font-family: Arial\" lang=\"EL\">Αντίο</span><span lang=\"EL\"> </span><span style=\"font-family: Arial\" lang=\"EL\">για</span><span lang=\"EL\"> </span><span style=\"font-family: Arial\" lang=\"EL\">πάντα</span></b>\r\n</p>\r\n<p class=\"MsoNormal\" style=\"text-align: left\" align=\"center\">\r\n<figure class=\"missing-image\" data-missing-image=\"true\" data-pagefind-ignore=\"true\">🖼 εικόνα μη διαθέσιμη</figure>\r\n</p>\r\n<p class=\"MsoNormal\" style=\"text-align: left\" align=\"left\">\r\n<span style=\"font-family: Arial\" lang=\"EL\">Μόνο</span><span lang=\"EL\"> </span><span style=\"font-family: Arial\" lang=\"EL\">οι</span><span lang=\"EL\"> </span><span style=\"font-family: Arial\" lang=\"EL\">φωτογραφίες</span><span lang=\"EL\"> </span><span style=\"font-family: Arial\" lang=\"EL\">απομένουν...</span><span lang=\"EL\"></span>\r\n</p>\r\n<p class=\"MsoNormal\">\r\n<span style=\"font-family: Arial\" lang=\"EL\">Η</span><span lang=\"EL\"> </span><span style=\"font-family: Arial\" lang=\"EL\">φώκια</span><span lang=\"EL\"> </span><span style=\"font-family: Arial\" lang=\"EL\">μονάχους</span><span lang=\"EL\"> </span><span style=\"font-family: Arial\" lang=\"EL\">της</span><span lang=\"EL\"> </span><span style=\"font-family: Arial\" lang=\"EL\">Καραϊβικής</span><span lang=\"EL\">, </span><span style=\"font-family: Arial\" lang=\"EL\">στενός</span><span lang=\"EL\"> </span><span style=\"font-family: Arial\" lang=\"EL\">συγγενής</span><span lang=\"EL\"> </span><span style=\"font-family: Arial\" lang=\"EL\">της</span><span lang=\"EL\"> </span><span style=\"font-family: Arial\" lang=\"EL\">μεσογειακής</span><span lang=\"EL\"> </span><span style=\"font-family: Arial\" lang=\"EL\">φώκιας</span><span lang=\"EL\">, </span><span style=\"font-family: Arial\" lang=\"EL\">ακολούθησε</span><span lang=\"EL\"> </span><span style=\"font-family: Arial\" lang=\"EL\">το</span><span lang=\"EL\"> </span><span style=\"font-family: Arial\" lang=\"EL\">δρόμο</span><span lang=\"EL\"> </span><span style=\"font-family: Arial\" lang=\"EL\">πολλών</span><span lang=\"EL\"> </span><span style=\"font-family: Arial\" lang=\"EL\">ακόμα</span><span lang=\"EL\"> </span><span style=\"font-family: Arial\" lang=\"EL\">ειδών</span><span lang=\"EL\"> </span><span style=\"font-family: Arial\" lang=\"EL\">και</span><span lang=\"EL\"> </span><span style=\"font-family: Arial\" lang=\"EL\">εξαφανίστηκε</span><span lang=\"EL\"> </span><span style=\"font-family: Arial\" lang=\"EL\">για</span><span lang=\"EL\"> </span><span style=\"font-family: Arial\" lang=\"EL\">πάντα</span><span lang=\"EL\">, </span><span style=\"font-family: Arial\" lang=\"EL\">επιβεβαίωσαν</span><span lang=\"DE-AT\"> </span><span lang=\"DE-AT\"> </span><span style=\"font-family: Arial\" lang=\"EL\">ομοσπονδιακοί</span><span lang=\"EL\"> </span><span style=\"font-family: Arial\" lang=\"EL\">αξιωματούχοι</span><span lang=\"EL\"> </span><span style=\"font-family: Arial\" lang=\"EL\">στις</span><span lang=\"EL\"> </span><span style=\"font-family: Arial\" lang=\"EL\">ΗΠΑ</span><span lang=\"EL\">.</span><span lang=\"EL\"></span>\r\n</p>\r\n<p class=\"MsoNormal\">\r\n<span style=\"font-family: Arial\" lang=\"DE-AT\">Η</span><span lang=\"DE-AT\"> </span><span style=\"font-family: Arial\" lang=\"DE-AT\">φώκια</span><span lang=\"DE-AT\"> </span><span style=\"font-family: Arial\" lang=\"DE-AT\">μοναχός</span><span lang=\"DE-AT\"> </span><span lang=\"DE-AT\">Monachus tropicalis </span><span style=\"font-family: Arial\" lang=\"DE-AT\">εθεάθη</span><span lang=\"DE-AT\"> </span><span style=\"font-family: Arial\" lang=\"DE-AT\">για</span><span lang=\"DE-AT\"> </span><span style=\"font-family: Arial\" lang=\"DE-AT\">τελευταία</span><span lang=\"DE-AT\"> </span><span style=\"font-family: Arial\" lang=\"DE-AT\">φορά</span><span lang=\"DE-AT\"> </span><span style=\"font-family: Arial\" lang=\"DE-AT\">το</span><span lang=\"DE-AT\"> 1952 </span><span style=\"font-family: Arial\" lang=\"DE-AT\">ανάμεσα</span><span lang=\"DE-AT\"> </span><span style=\"font-family: Arial\" lang=\"DE-AT\">στη</span><span lang=\"DE-AT\"> </span><span style=\"font-family: Arial\" lang=\"DE-AT\">Τζαμάικα</span><span lang=\"DE-AT\"> </span><span style=\"font-family: Arial\" lang=\"DE-AT\">και</span><span lang=\"DE-AT\"> </span><span style=\"font-family: Arial\" lang=\"DE-AT\">τη</span><span lang=\"DE-AT\"> </span><span style=\"font-family: Arial\" lang=\"DE-AT\">χερσόνησο</span><span lang=\"DE-AT\"> </span><span style=\"font-family: Arial\" lang=\"DE-AT\">Γιουκάταν</span><span lang=\"DE-AT\"> </span><span style=\"font-family: Arial\" lang=\"DE-AT\">του</span><span lang=\"DE-AT\"> </span><span style=\"font-family: Arial\" lang=\"DE-AT\">Μεξικού</span><span lang=\"DE-AT\">. </span>\r\n</p>\r\n<p class=\"MsoNormal\">\r\n<span style=\"font-family: Arial\" lang=\"DE-AT\">Οι</span><span lang=\"DE-AT\"> </span><span style=\"font-family: Arial\" lang=\"DE-AT\">επιστήμονες</span><span lang=\"DE-AT\"> </span><span style=\"font-family: Arial\" lang=\"DE-AT\">υποψιάζονταν</span><span lang=\"DE-AT\"> </span><span style=\"font-family: Arial\" lang=\"DE-AT\">εδώ</span><span lang=\"DE-AT\"> </span><span style=\"font-family: Arial\" lang=\"DE-AT\">και</span><span lang=\"DE-AT\"> </span><span style=\"font-family: Arial\" lang=\"DE-AT\">καιρό</span><span lang=\"DE-AT\"> </span><span style=\"font-family: Arial\" lang=\"DE-AT\">ότι</span><span lang=\"DE-AT\"> </span><span style=\"font-family: Arial\" lang=\"DE-AT\">είχε</span><span lang=\"DE-AT\"> </span><span style=\"font-family: Arial\" lang=\"DE-AT\">εξαφανιστεί</span><span lang=\"DE-AT\"> </span><span style=\"font-family: Arial\" lang=\"DE-AT\">και</span><span lang=\"DE-AT\"> </span><span style=\"font-family: Arial\" lang=\"DE-AT\">προειδοποιούν</span><span lang=\"DE-AT\"> </span><span style=\"font-family: Arial\" lang=\"DE-AT\">τώρα</span><span lang=\"DE-AT\"> </span><span style=\"font-family: Arial\" lang=\"DE-AT\">ότι</span><span lang=\"DE-AT\"> </span><span style=\"font-family: Arial\" lang=\"DE-AT\">η</span><span lang=\"DE-AT\"> </span><span style=\"font-family: Arial\" lang=\"DE-AT\">φώκια</span><span lang=\"DE-AT\"> </span><span style=\"font-family: Arial\" lang=\"DE-AT\">μονάχους</span><span lang=\"DE-AT\"> </span><span style=\"font-family: Arial\" lang=\"DE-AT\">της</span><span lang=\"DE-AT\"> </span><span style=\"font-family: Arial\" lang=\"DE-AT\">Χαβάης</span><span lang=\"DE-AT\"> </span><span lang=\"DE-AT\">Monachus schauinslandi </span><span style=\"font-family: Arial\" lang=\"DE-AT\">και</span><span lang=\"DE-AT\">\r\n</span><span style=\"font-family: Arial\" lang=\"DE-AT\">ο</span><span lang=\"DE-AT\"> </span><span style=\"font-family: Arial\" lang=\"DE-AT\">ξάδελφός</span><span lang=\"DE-AT\"> </span><span style=\"font-family: Arial\" lang=\"DE-AT\">της</span><span lang=\"DE-AT\"> </span><span style=\"font-family: Arial\" lang=\"DE-AT\">στη</span><span lang=\"DE-AT\"> </span><span style=\"font-family: Arial\" lang=\"DE-AT\">Μεσόγειο</span><span lang=\"DE-AT\"> </span><span lang=\"DE-AT\">Monachus monachus, </span><span style=\"font-family: Arial\" lang=\"DE-AT\">θα</span><span lang=\"DE-AT\"> </span><span style=\"font-family: Arial\" lang=\"DE-AT\">έχουν</span><span lang=\"DE-AT\"> </span><span style=\"font-family: Arial\" lang=\"DE-AT\">την</span><span lang=\"DE-AT\"> </span><span style=\"font-family: Arial\" lang=\"DE-AT\">ίδια</span><span lang=\"DE-AT\"> </span><span style=\"font-family: Arial\" lang=\"DE-AT\">κατάληξη</span><span lang=\"DE-AT\">.</span>\r\n</p>\r\n<p class=\"MsoNormal\">\r\n<span lang=\"DE-AT\">«</span><span style=\"font-family: Arial\" lang=\"DE-AT\">Ελπίζω</span><span lang=\"DE-AT\">\r\n</span><span style=\"font-family: Arial\" lang=\"DE-AT\">ότι</span><span lang=\"DE-AT\"> </span><span style=\"font-family: Arial\" lang=\"DE-AT\">πήραμε</span><span lang=\"DE-AT\"> </span><span style=\"font-family: Arial\" lang=\"DE-AT\">το</span><span lang=\"DE-AT\"> </span><span style=\"font-family: Arial\" lang=\"DE-AT\">μάθημα</span><span lang=\"DE-AT\"> </span><span style=\"font-family: Arial\" lang=\"DE-AT\">από</span><span lang=\"DE-AT\"> </span><span style=\"font-family: Arial\" lang=\"DE-AT\">την</span><span lang=\"DE-AT\"> </span><span style=\"font-family: Arial\" lang=\"DE-AT\">εξάλειψη</span><span lang=\"DE-AT\"> </span><span style=\"font-family: Arial\" lang=\"DE-AT\">της</span><span lang=\"DE-AT\"> </span><span style=\"font-family: Arial\" lang=\"DE-AT\">φώκιας</span><span lang=\"DE-AT\"> </span><span style=\"font-family: Arial\" lang=\"DE-AT\">μονάχους</span><span lang=\"DE-AT\"> </span><span style=\"font-family: Arial\" lang=\"DE-AT\">της</span><span lang=\"DE-AT\"> </span><span style=\"font-family: Arial\" lang=\"DE-AT\">Καραϊβικής</span><span lang=\"DE-AT\"> </span><span style=\"font-family: Arial\" lang=\"DE-AT\">και</span><span lang=\"DE-AT\"> </span><span style=\"font-family: Arial\" lang=\"DE-AT\">μπορούμε</span><span lang=\"DE-AT\"> </span><span style=\"font-family: Arial\" lang=\"DE-AT\">να</span><span lang=\"DE-AT\"> </span><span style=\"font-family: Arial\" lang=\"DE-AT\">παράσχουμε</span><span lang=\"DE-AT\"> </span><span style=\"font-family: Arial\" lang=\"DE-AT\">καλύτερη</span><span lang=\"DE-AT\"> </span><span style=\"font-family: Arial\" lang=\"DE-AT\">προστασία</span><span lang=\"DE-AT\"> </span><span style=\"font-family: Arial\" lang=\"DE-AT\">για</span><span lang=\"DE-AT\"> </span><span style=\"font-family: Arial\" lang=\"DE-AT\">τους</span><span lang=\"DE-AT\"> </span><span style=\"font-family: Arial\" lang=\"DE-AT\">συγγενείς</span><span lang=\"DE-AT\"> </span><span style=\"font-family: Arial\" lang=\"DE-AT\">της</span><span lang=\"DE-AT\"> </span><span style=\"font-family: Arial\" lang=\"DE-AT\">στη</span><span lang=\"DE-AT\"> </span><span style=\"font-family: Arial\" lang=\"DE-AT\">Χαβάη</span><span lang=\"DE-AT\"> </span><span style=\"font-family: Arial\" lang=\"DE-AT\">και</span><span lang=\"DE-AT\"> </span><span style=\"font-family: Arial\" lang=\"DE-AT\">τη</span><span lang=\"DE-AT\"> </span><span style=\"font-family: Arial\" lang=\"DE-AT\">Μεσόγειο</span><span lang=\"DE-AT\">» </span><span style=\"font-family: Arial\" lang=\"DE-AT\">σχολίασε</span><span lang=\"DE-AT\"> </span><span style=\"font-family: Arial\" lang=\"DE-AT\">ο</span><span lang=\"DE-AT\"> </span><span style=\"font-family: Arial\" lang=\"DE-AT\">Κάιλ</span><span lang=\"DE-AT\"> </span><span style=\"font-family: Arial\" lang=\"DE-AT\">Μπέικερ</span><span lang=\"DE-AT\">, </span><span style=\"font-family: Arial\" lang=\"DE-AT\">βιολόγος</span><span lang=\"DE-AT\"> </span><span style=\"font-family: Arial\" lang=\"DE-AT\">της</span><span lang=\"DE-AT\"> </span><span style=\"font-family: Arial\" lang=\"DE-AT\">Υπηρεσίας</span><span lang=\"DE-AT\"> </span><span style=\"font-family: Arial\" lang=\"DE-AT\">Αλιευμάτων</span><span lang=\"DE-AT\"> </span><span style=\"font-family: Arial\" lang=\"DE-AT\">της</span><span lang=\"DE-AT\"> </span><span style=\"font-family: Arial\" lang=\"DE-AT\">αμερικανικής</span><span lang=\"DE-AT\"> </span><span style=\"font-family: Arial\" lang=\"DE-AT\">Εθνικής</span><span lang=\"DE-AT\"> </span><span style=\"font-family: Arial\" lang=\"DE-AT\">Υπηρεσίας</span><span lang=\"DE-AT\"> </span><span style=\"font-family: Arial\" lang=\"DE-AT\">Ωκεανών</span><span lang=\"DE-AT\"> </span><span style=\"font-family: Arial\" lang=\"DE-AT\">και</span><span lang=\"DE-AT\"> </span><span style=\"font-family: Arial\" lang=\"DE-AT\">Ατμόσφαιρας</span><span lang=\"DE-AT\"> (</span><span lang=\"DE-AT\">NOAA).</span>\r\n</p>\r\n<p class=\"MsoNormal\">\r\n<span style=\"font-family: Arial\" lang=\"DE-AT\">Επισήμανε</span><span lang=\"DE-AT\"> </span><span style=\"font-family: Arial\" lang=\"DE-AT\">ότι</span><span lang=\"DE-AT\"> </span><span style=\"font-family: Arial\" lang=\"DE-AT\">σήμερα</span><span lang=\"DE-AT\"> </span><span style=\"font-family: Arial\" lang=\"DE-AT\">υπάρχουν</span><span lang=\"DE-AT\"> </span><span style=\"font-family: Arial\" lang=\"DE-AT\">περίπου</span><span lang=\"DE-AT\"> 1.500 </span><span style=\"font-family: Arial\" lang=\"DE-AT\">φώκιες</span><span lang=\"DE-AT\"> </span><span style=\"font-family: Arial\" lang=\"DE-AT\">του</span><span lang=\"DE-AT\"> </span><span style=\"font-family: Arial\" lang=\"DE-AT\">ίδιου</span><span lang=\"DE-AT\"> </span><span style=\"font-family: Arial\" lang=\"DE-AT\">γένους</span><span lang=\"DE-AT\"> </span><span style=\"font-family: Arial\" lang=\"DE-AT\">στη</span><span lang=\"DE-AT\"> </span><span style=\"font-family: Arial\" lang=\"DE-AT\">Χαβάη</span><span lang=\"DE-AT\"> </span><span style=\"font-family: Arial\" lang=\"DE-AT\">και</span><span lang=\"DE-AT\"> </span><span style=\"font-family: Arial\" lang=\"DE-AT\">λιγότερες</span><span lang=\"DE-AT\"> </span><span style=\"font-family: Arial\" lang=\"DE-AT\">από</span><span lang=\"DE-AT\"> 500 </span><span style=\"font-family: Arial\" lang=\"DE-AT\">στη</span><span lang=\"DE-AT\"> </span><span style=\"font-family: Arial\" lang=\"DE-AT\">Μεσόγειο</span><span lang=\"DE-AT\">.</span>\r\n</p>\r\n<p class=\"MsoNormal\">\r\n<b><span style=\"font-family: Arial\" lang=\"DE-AT\">Κρίσιμο</span><span lang=\"DE-AT\"> </span><span style=\"font-family: Arial\" lang=\"DE-AT\">όριο</span></b>\r\n</p>\r\n<p class=\"MsoNormal\">\r\n<span style=\"font-family: Arial\" lang=\"DE-AT\">Οι</span><span lang=\"DE-AT\"> </span><span style=\"font-family: Arial\" lang=\"DE-AT\">φώκιες</span><span lang=\"DE-AT\"> </span><span style=\"font-family: Arial\" lang=\"DE-AT\">μονάχους</span><span lang=\"DE-AT\"> </span><span style=\"font-family: Arial\" lang=\"DE-AT\">είναι</span><span lang=\"DE-AT\"> </span><span style=\"font-family: Arial\" lang=\"DE-AT\">ιδιαίτερα</span><span lang=\"DE-AT\"> </span><span style=\"font-family: Arial\" lang=\"DE-AT\">ευάλωτες</span><span lang=\"DE-AT\"> </span><span style=\"font-family: Arial\" lang=\"DE-AT\">στην</span><span lang=\"DE-AT\"> </span><span style=\"font-family: Arial\" lang=\"DE-AT\">ανθρώπινη</span><span lang=\"DE-AT\"> </span><span style=\"font-family: Arial\" lang=\"DE-AT\">δραστηριότητα</span><span lang=\"DE-AT\"> </span><span style=\"font-family: Arial\" lang=\"DE-AT\">και</span><span lang=\"DE-AT\"> </span><span style=\"font-family: Arial\" lang=\"DE-AT\">ήταν</span><span lang=\"DE-AT\"> </span><span style=\"font-family: Arial\" lang=\"DE-AT\">εύκολος</span><span lang=\"DE-AT\"> </span><span style=\"font-family: Arial\" lang=\"DE-AT\">στόχος</span><span lang=\"DE-AT\"> </span><span style=\"font-family: Arial\" lang=\"DE-AT\">για</span><span lang=\"DE-AT\"> </span><span style=\"font-family: Arial\" lang=\"DE-AT\">τους</span><span lang=\"DE-AT\"> </span><span style=\"font-family: Arial\" lang=\"DE-AT\">κυνηγούς</span><span lang=\"DE-AT\">, </span><span style=\"font-family: Arial\" lang=\"DE-AT\">καθώς</span><span lang=\"DE-AT\"> </span><span style=\"font-family: Arial\" lang=\"DE-AT\">συνήθιζαν</span><span lang=\"DE-AT\"> </span><span style=\"font-family: Arial\" lang=\"DE-AT\">να</span><span lang=\"DE-AT\"> </span><span style=\"font-family: Arial\" lang=\"DE-AT\">λιάζονται</span><span lang=\"DE-AT\"> </span><span style=\"font-family: Arial\" lang=\"DE-AT\">και</span><span lang=\"DE-AT\"> </span><span style=\"font-family: Arial\" lang=\"DE-AT\">να</span><span lang=\"DE-AT\"> </span><span style=\"font-family: Arial\" lang=\"DE-AT\">γεννούν</span><span lang=\"DE-AT\"> </span><span style=\"font-family: Arial\" lang=\"DE-AT\">τα</span><span lang=\"DE-AT\"> </span><span style=\"font-family: Arial\" lang=\"DE-AT\">μικρά</span><span lang=\"DE-AT\"> </span><span style=\"font-family: Arial\" lang=\"DE-AT\">τους</span><span lang=\"DE-AT\"> </span><span style=\"font-family: Arial\" lang=\"DE-AT\">στην</span><span lang=\"DE-AT\"> </span><span style=\"font-family: Arial\" lang=\"DE-AT\">παραλία</span><span lang=\"DE-AT\">.</span><span lang=\"DE-AT\">  </span><span style=\"font-family: Arial\" lang=\"DE-AT\">Σήμερα</span><span lang=\"DE-AT\"> </span><span style=\"font-family: Arial\" lang=\"DE-AT\">αντιμετωπίζουν</span><span lang=\"DE-AT\"> </span><span style=\"font-family: Arial\" lang=\"DE-AT\">άλλες</span><span lang=\"DE-AT\"> </span><span style=\"font-family: Arial\" lang=\"DE-AT\">προκλήσεις</span><span lang=\"DE-AT\">, </span><span style=\"font-family: Arial\" lang=\"DE-AT\">όπως</span><span lang=\"DE-AT\"> </span><span style=\"font-family: Arial\" lang=\"DE-AT\">η</span><span lang=\"DE-AT\"> </span><span style=\"font-family: Arial\" lang=\"DE-AT\">παράκτια</span><span lang=\"DE-AT\"> </span><span style=\"font-family: Arial\" lang=\"DE-AT\">ανάπτυξη</span><span lang=\"DE-AT\">, </span><span style=\"font-family: Arial\" lang=\"DE-AT\">η</span><span lang=\"DE-AT\"> </span><span style=\"font-family: Arial\" lang=\"DE-AT\">κλιματική</span><span lang=\"DE-AT\"> </span><span style=\"font-family: Arial\" lang=\"DE-AT\">αλλαγή</span><span lang=\"DE-AT\"> </span><span style=\"font-family: Arial\" lang=\"DE-AT\">και</span><span lang=\"DE-AT\"> </span><span style=\"font-family: Arial\" lang=\"DE-AT\">τα</span><span lang=\"DE-AT\"> </span><span style=\"font-family: Arial\" lang=\"DE-AT\">δίχτυα</span><span lang=\"DE-AT\">.</span>\r\n</p>\r\n<p class=\"MsoNormal\">\r\n<span style=\"font-family: Arial\" lang=\"DE-AT\">Ακόμα</span><span lang=\"DE-AT\"> </span><span style=\"font-family: Arial\" lang=\"DE-AT\">και</span><span lang=\"DE-AT\"> </span><span style=\"font-family: Arial\" lang=\"DE-AT\">αν</span><span lang=\"DE-AT\"> </span><span style=\"font-family: Arial\" lang=\"DE-AT\">υπάρξει</span><span lang=\"DE-AT\"> </span><span style=\"font-family: Arial\" lang=\"DE-AT\">αποτελεσματική</span><span lang=\"DE-AT\"> </span><span style=\"font-family: Arial\" lang=\"DE-AT\">προστασία</span><span lang=\"DE-AT\">, </span><span style=\"font-family: Arial\" lang=\"DE-AT\">οι</span><span lang=\"DE-AT\"> </span><span style=\"font-family: Arial\" lang=\"DE-AT\">πληθυσμοί</span><span lang=\"DE-AT\"> </span><span style=\"font-family: Arial\" lang=\"DE-AT\">δεν</span><span lang=\"DE-AT\"> </span><span style=\"font-family: Arial\" lang=\"DE-AT\">μπορούν</span><span lang=\"DE-AT\"> </span><span style=\"font-family: Arial\" lang=\"DE-AT\">να</span><span lang=\"DE-AT\"> </span><span style=\"font-family: Arial\" lang=\"DE-AT\">ανακάμψουν</span><span lang=\"DE-AT\"> </span><span style=\"font-family: Arial\" lang=\"DE-AT\">αν</span><span lang=\"DE-AT\"> </span><span style=\"font-family: Arial\" lang=\"DE-AT\">πέσουν</span><span lang=\"DE-AT\"> </span><span style=\"font-family: Arial\" lang=\"DE-AT\">κάτω</span><span lang=\"DE-AT\"> </span><span style=\"font-family: Arial\" lang=\"DE-AT\">από</span><span lang=\"DE-AT\"> </span><span style=\"font-family: Arial\" lang=\"DE-AT\">ένα</span><span lang=\"DE-AT\"> </span><span style=\"font-family: Arial\" lang=\"DE-AT\">κρίσιμο</span><span lang=\"DE-AT\"> </span><span style=\"font-family: Arial\" lang=\"DE-AT\">όριο</span><span lang=\"DE-AT\"> </span><span style=\"font-family: Arial\" lang=\"DE-AT\">και</span><span lang=\"DE-AT\"> </span><span style=\"font-family: Arial\" lang=\"DE-AT\">χάσουν</span><span lang=\"DE-AT\"> </span><span style=\"font-family: Arial\" lang=\"DE-AT\">τη</span><span lang=\"DE-AT\"> </span><span style=\"font-family: Arial\" lang=\"DE-AT\">γενετική</span><span lang=\"DE-AT\"> </span><span style=\"font-family: Arial\" lang=\"DE-AT\">τους</span><span lang=\"DE-AT\"> </span><span style=\"font-family: Arial\" lang=\"DE-AT\">ποικιλότητα</span><span lang=\"DE-AT\">. </span>\r\n</p>\r\n<p class=\"MsoNormal\">\r\n<span lang=\"DE-AT\">«</span><span style=\"font-family: Arial\" lang=\"DE-AT\">Όταν</span><span lang=\"DE-AT\">\r\n</span><span style=\"font-family: Arial\" lang=\"DE-AT\">οι</span><span lang=\"DE-AT\"> </span><span style=\"font-family: Arial\" lang=\"DE-AT\">πληθυσμοί</span><span lang=\"DE-AT\"> </span><span style=\"font-family: Arial\" lang=\"DE-AT\">είναι</span><span lang=\"DE-AT\"> </span><span style=\"font-family: Arial\" lang=\"DE-AT\">πολύ</span><span lang=\"DE-AT\"> </span><span style=\"font-family: Arial\" lang=\"DE-AT\">μικροί</span><span lang=\"DE-AT\">, </span><span style=\"font-family: Arial\" lang=\"DE-AT\">γίνονται</span><span lang=\"DE-AT\"> </span><span style=\"font-family: Arial\" lang=\"DE-AT\">ασταθείς</span><span lang=\"DE-AT\">. </span><span style=\"font-family: Arial\" lang=\"DE-AT\">Γίνονται</span><span lang=\"DE-AT\"> </span><span style=\"font-family: Arial\" lang=\"DE-AT\">πολύ</span><span lang=\"DE-AT\"> </span><span style=\"font-family: Arial\" lang=\"DE-AT\">ευάλωτοι</span><span lang=\"DE-AT\"> </span><span style=\"font-family: Arial\" lang=\"DE-AT\">σε</span><span lang=\"DE-AT\"> </span><span style=\"font-family: Arial\" lang=\"DE-AT\">απειλές</span><span lang=\"DE-AT\"> </span><span style=\"font-family: Arial\" lang=\"DE-AT\">όπως</span><span lang=\"DE-AT\"> </span><span style=\"font-family: Arial\" lang=\"DE-AT\">οι</span><span lang=\"DE-AT\"> </span><span style=\"font-family: Arial\" lang=\"DE-AT\">ασθένειες</span><span lang=\"DE-AT\"> </span><span style=\"font-family: Arial\" lang=\"DE-AT\">και</span><span lang=\"DE-AT\"> </span><span style=\"font-family: Arial\" lang=\"DE-AT\">οι</span><span lang=\"DE-AT\"> </span><span style=\"font-family: Arial\" lang=\"DE-AT\">επιθέσεις</span><span lang=\"DE-AT\"> </span><span style=\"font-family: Arial\" lang=\"DE-AT\">από</span><span lang=\"DE-AT\"> </span><span style=\"font-family: Arial\" lang=\"DE-AT\">καρχαρίες</span><span lang=\"DE-AT\">» </span><span style=\"font-family: Arial\" lang=\"DE-AT\">εξήγησε</span><span lang=\"DE-AT\"> </span><span style=\"font-family: Arial\" lang=\"DE-AT\">ο</span><span lang=\"DE-AT\"> </span><span style=\"font-family: Arial\" lang=\"DE-AT\">Μπέικερ</span><span lang=\"DE-AT\">.</span>\r\n</p>\r\n<p class=\"MsoNormal\">\r\n<span style=\"font-family: Arial\" lang=\"DE-AT\">Η</span><span lang=\"DE-AT\"> </span><span style=\"font-family: Arial\" lang=\"DE-AT\">φώκια</span><span lang=\"DE-AT\"> </span><span style=\"font-family: Arial\" lang=\"DE-AT\">μονάχους</span><span lang=\"DE-AT\"> </span><span style=\"font-family: Arial\" lang=\"DE-AT\">της</span><span lang=\"DE-AT\"> </span><span style=\"font-family: Arial\" lang=\"DE-AT\">Καραϊβικής</span><span lang=\"DE-AT\"> </span><span style=\"font-family: Arial\" lang=\"DE-AT\">ανακαλύφθηκε</span><span lang=\"DE-AT\"> </span><span style=\"font-family: Arial\" lang=\"DE-AT\">στη</span><span lang=\"DE-AT\"> </span><span style=\"font-family: Arial\" lang=\"DE-AT\">διάρκεια</span><span lang=\"DE-AT\"> </span><span style=\"font-family: Arial\" lang=\"DE-AT\">της</span><span lang=\"DE-AT\"> </span><span style=\"font-family: Arial\" lang=\"DE-AT\">δεύτερης</span><span lang=\"DE-AT\"> </span><span style=\"font-family: Arial\" lang=\"DE-AT\">αποστολής</span><span lang=\"DE-AT\"> </span><span style=\"font-family: Arial\" lang=\"DE-AT\">του</span><span lang=\"DE-AT\"> </span><span style=\"font-family: Arial\" lang=\"DE-AT\">Χριστόφορου</span><span lang=\"DE-AT\"> </span><span style=\"font-family: Arial\" lang=\"DE-AT\">Κολόμβου</span><span lang=\"DE-AT\"> </span><span style=\"font-family: Arial\" lang=\"DE-AT\">το</span><span lang=\"DE-AT\"> 1494.</span>\r\n</p>\r\n<p class=\"MsoNormal\">\r\n<b><span style=\"font-family: Arial\" lang=\"DE-AT\">Κάποτε</span><span lang=\"DE-AT\"> </span><span style=\"font-family: Arial\" lang=\"DE-AT\">ο</span><span lang=\"DE-AT\"> </span><span style=\"font-family: Arial\" lang=\"DE-AT\">πληθυσμός</span><span lang=\"DE-AT\"> </span><span style=\"font-family: Arial\" lang=\"DE-AT\">της</span><span lang=\"DE-AT\"> </span><span style=\"font-family: Arial\" lang=\"DE-AT\">αριθμούσε</span><span lang=\"DE-AT\"> </span><span style=\"font-family: Arial\" lang=\"DE-AT\">πάνω</span><span lang=\"DE-AT\"> </span><span style=\"font-family: Arial\" lang=\"DE-AT\">από</span><span lang=\"DE-AT\"> 250.000 </span><span style=\"font-family: Arial\" lang=\"DE-AT\">άτομα</span><span lang=\"DE-AT\">.</span></b>\r\n</p>\r\n<p class=\"MsoNormal\">\r\n<span style=\"font-family: Arial\" lang=\"DE-AT\">Από</span><span lang=\"DE-AT\"> </span><span style=\"font-family: Arial\" lang=\"DE-AT\">τον</span><span lang=\"DE-AT\"> 18</span><span style=\"font-family: Arial\" lang=\"DE-AT\">ο</span><span lang=\"DE-AT\"> </span><span style=\"font-family: Arial\" lang=\"DE-AT\">έως</span><span lang=\"DE-AT\"> </span><span style=\"font-family: Arial\" lang=\"DE-AT\">τον</span><span lang=\"DE-AT\"> 20</span><span style=\"font-family: Arial\" lang=\"DE-AT\">ό</span><span lang=\"DE-AT\"> </span><span style=\"font-family: Arial\" lang=\"DE-AT\">αιώνα</span><span lang=\"DE-AT\"> </span><span style=\"font-family: Arial\" lang=\"DE-AT\">οι</span><span lang=\"DE-AT\"> </span><span style=\"font-family: Arial\" lang=\"DE-AT\">φώκιες</span><span lang=\"DE-AT\"> </span><span style=\"font-family: Arial\" lang=\"DE-AT\">μονάχους</span><span lang=\"DE-AT\"> </span><span style=\"font-family: Arial\" lang=\"DE-AT\">ήταν</span><span lang=\"DE-AT\"> </span><span style=\"font-family: Arial\" lang=\"DE-AT\">περιζήτητες</span><span lang=\"DE-AT\"> </span><span style=\"font-family: Arial\" lang=\"DE-AT\">για</span><span lang=\"DE-AT\"> </span><span style=\"font-family: Arial\" lang=\"DE-AT\">το</span><span lang=\"DE-AT\"> </span><span style=\"font-family: Arial\" lang=\"DE-AT\">λίπος</span><span lang=\"DE-AT\"> </span><span style=\"font-family: Arial\" lang=\"DE-AT\">τους</span><span lang=\"DE-AT\">, </span><span style=\"font-family: Arial\" lang=\"DE-AT\">που</span><span lang=\"DE-AT\"> </span><span style=\"font-family: Arial\" lang=\"DE-AT\">μετατρεπόταν</span><span lang=\"DE-AT\"> </span><span style=\"font-family: Arial\" lang=\"DE-AT\">σε</span><span lang=\"DE-AT\"> </span><span style=\"font-family: Arial\" lang=\"DE-AT\">λάδι</span><span lang=\"DE-AT\"> </span><span style=\"font-family: Arial\" lang=\"DE-AT\">και</span><span lang=\"DE-AT\"> </span><span style=\"font-family: Arial\" lang=\"DE-AT\">χρησιμοποιείτο</span><span lang=\"DE-AT\"> </span><span style=\"font-family: Arial\" lang=\"DE-AT\">ως</span><span lang=\"DE-AT\"> </span><span style=\"font-family: Arial\" lang=\"DE-AT\">λιπαντικό</span><span lang=\"DE-AT\"> </span><span style=\"font-family: Arial\" lang=\"DE-AT\">και</span><span lang=\"DE-AT\"> </span><span style=\"font-family: Arial\" lang=\"DE-AT\">ως</span><span lang=\"DE-AT\"> </span><span style=\"font-family: Arial\" lang=\"DE-AT\">επίστρωση</span><span lang=\"DE-AT\"> </span><span style=\"font-family: Arial\" lang=\"DE-AT\">για</span><span lang=\"DE-AT\"> </span><span style=\"font-family: Arial\" lang=\"DE-AT\">την</span><span lang=\"DE-AT\"> </span><span style=\"font-family: Arial\" lang=\"DE-AT\">κοιλιά</span><span lang=\"DE-AT\"> </span><span style=\"font-family: Arial\" lang=\"DE-AT\">πλοίων</span><span lang=\"DE-AT\">. </span><span style=\"font-family: Arial\" lang=\"DE-AT\">Το</span><span lang=\"DE-AT\"> </span><span style=\"font-family: Arial\" lang=\"DE-AT\">δέρμα</span><span lang=\"DE-AT\"> </span><span style=\"font-family: Arial\" lang=\"DE-AT\">τους</span><span lang=\"DE-AT\"> </span><span style=\"font-family: Arial\" lang=\"DE-AT\">γινόταν</span><span lang=\"DE-AT\"> </span><span style=\"font-family: Arial\" lang=\"DE-AT\">τσάντες</span><span lang=\"DE-AT\"> </span><span style=\"font-family: Arial\" lang=\"DE-AT\">και</span><span lang=\"DE-AT\"> </span><span style=\"font-family: Arial\" lang=\"DE-AT\">ρούχα</span><span lang=\"DE-AT\">.</span>\r\n</p>\r\n<p class=\"MsoNormal\">\r\n<i><span lang=\"DE-AT\">Πηγή: Newsroom </span><span style=\"font-family: Arial\" lang=\"DE-AT\">ΔΟΛ</span><span lang=\"DE-AT\"> (07.06.2008) , </span><span style=\"font-family: Arial\" lang=\"DE-AT\">με</span><span lang=\"DE-AT\"> </span><span style=\"font-family: Arial\" lang=\"DE-AT\">πληροφορίες</span><span lang=\"DE-AT\"> </span><span style=\"font-family: Arial\" lang=\"DE-AT\">από</span><span lang=\"DE-AT\"> </span><span lang=\"DE-AT\">Associated\r\nPress</span></i>\r\n</p>",
  "text": "Αντίο για πάντα Μόνο οι φωτογραφίες απομένουν... Η φώκια μονάχους της Καραϊβικής , στενός συγγενής της μεσογειακής φώκιας , ακολούθησε το δρόμο πολλών ακόμα ειδών και εξαφανίστηκε για πάντα , επιβεβαίωσαν ομοσπονδιακοί αξιωματούχοι στις ΗΠΑ . Η φώκια μοναχός Monachus tropicalis εθεάθη για τελευταία φορά το 1952 ανάμεσα στη Τζαμάικα και τη χερσόνησο Γιουκάταν του Μεξικού . Οι επιστήμονες υποψιάζονταν εδώ και καιρό ότι είχε εξαφανιστεί και προειδοποιούν τώρα ότι η φώκια μονάχους της Χαβάης Monachus schauinslandi και ο ξάδελφός της στη Μεσόγειο Monachus monachus, θα έχουν την ίδια κατάληξη . « Ελπίζω ότι πήραμε το μάθημα από την εξάλειψη της φώκιας μονάχους της Καραϊβικής και μπορούμε να παράσχουμε καλύτερη προστασία για τους συγγενείς της στη Χαβάη και τη Μεσόγειο » σχολίασε ο Κάιλ Μπέικερ , βιολόγος της Υπηρεσίας Αλιευμάτων της αμερικανικής Εθνικής Υπηρεσίας Ωκεανών και Ατμόσφαιρας ( NOAA). Επισήμανε ότι σήμερα υπάρχουν περίπου 1.500 φώκιες του ίδιου γένους στη Χαβάη και λιγότερες από 500 στη Μεσόγειο . Κρίσιμο όριο Οι φώκιες μονάχους είναι ιδιαίτερα ευάλωτες στην ανθρώπινη δραστηριότητα και ήταν εύκολος στόχος για τους κυνηγούς , καθώς συνήθιζαν να λιάζονται και να γεννούν τα μικρά τους στην παραλία . Σήμερα αντιμετωπίζουν άλλες προκλήσεις , όπως η παράκτια ανάπτυξη , η κλιματική αλλαγή και τα δίχτυα . Ακόμα και αν υπάρξει αποτελεσματική προστασία , οι πληθυσμοί δεν μπορούν να ανακάμψουν αν πέσουν κάτω από ένα κρίσιμο όριο και χάσουν τη γενετική τους ποικιλότητα . « Όταν οι πληθυσμοί είναι πολύ μικροί , γίνονται ασταθείς . Γίνονται πολύ ευάλωτοι σε απειλές όπως οι ασθένειες και οι επιθέσεις από καρχαρίες » εξήγησε ο Μπέικερ . Η φώκια μονάχους της Καραϊβικής ανακαλύφθηκε στη διάρκεια της δεύτερης αποστολής του Χριστόφορου Κολόμβου το 1494. Κάποτε ο πληθυσμός της αριθμούσε πάνω από 250.000 άτομα . Από τον 18 ο έως τον 20 ό αιώνα οι φώκιες μονάχους ήταν περιζήτητες για το λίπος τους , που μετατρεπόταν σε λάδι και χρησιμοποιείτο ως λιπαντικό και ως επίστρωση για την κοιλιά πλοίων . Το δέρμα τους γινόταν τσάντες και ρούχα . Πηγή: Newsroom ΔΟΛ (07.06.2008) , με πληροφορίες από Associated Press"
}