{
  "id": 248,
  "title": "Gute Worte Olympos 6 Αντώνης",
  "slug": "gute-worte-olympos-6-antonis-248",
  "sectionId": 2,
  "sectionTitle": "Με δυο λόγια",
  "sectionSlug": "me-dyo-logia-2",
  "categoryId": 3,
  "categoryTitle": "Σύντομα",
  "categorySlug": "syntoma-3",
  "date": "2009-10-24T18:56:44",
  "created": "2009-10-24T18:57:12",
  "published": true,
  "state": 1,
  "frontpage": false,
  "hits": 64,
  "excerpt": "Συγχαρητήρια για τον αγώνα σας και κυρίως το κουράγιο σας. Κ. Αντώνης",
  "html": "<p>\r\nΣυγχαρητήρια για τον αγώνα σας και κυρίως το κουράγιο σας.\r\n</p>\r\n<p>\r\nΚ. Αντώνης\r\n</p>",
  "text": "Συγχαρητήρια για τον αγώνα σας και κυρίως το κουράγιο σας. Κ. Αντώνης"
}